{
    "buttons": [
        {
            "label": "Website",
            "svg": "aspect.svg",
            "href": "/"
        },
        {
            "label": "Publish",
            "svg": "books.svg",
            "href": "/admin/publish"
        },
        {
            "label": "Users",
            "svg": "emoticon.svg",
            "href": "/admin/users"
        },
        {
            "label": "Modules",
            "svg": "extension.svg",
            "href": "/admin/modules"
        },
        {
            "label": "Themes",
            "svg": "colors.svg",
            "href": "/admin/themes"
        },
        {
            "label": "Files",
            "svg": "folder.svg",
            "href": "/admin/files"
        },
        {
            "label": "Settings",
            "svg": "settings.svg",
            "href": "/admin/settings"
        }

    ]
}
